{
  "project_info": {
    "project_number": "643358847305",
    "firebase_url": "https://presence-3183d-default-rtdb.europe-west1.firebasedatabase.app",
    "project_id": "presence-3183d",
    "storage_bucket": "presence-3183d.appspot.com"
  },
  "client": [
    {
      "client_info": {
        "mobilesdk_app_id": "1:643358847305:android:752e843ec63413bb036a98",
        "android_client_info": {
          "package_name": "com.adam.presence"
        }
      },
      "oauth_client": [
        {
          "client_id": "643358847305-drs500tj7uj36fbnmstagsqfiokbohh2.apps.googleusercontent.com",
          "client_type": 3
        }
      ],
      "api_key": [
        {
          "current_key": "AIzaSyDTnI_x3paZQFpJAlvkjn3Cwuc3w1P_vGI"
        }
      ],
      "services": {
        "appinvite_service": {
          "other_platform_oauth_client": [
            {
              "client_id": "643358847305-drs500tj7uj36fbnmstagsqfiokbohh2.apps.googleusercontent.com",
              "client_type": 3
            }
          ]
        }
      }
    }
  ],
  "configuration_version": "1"
}